rich_monokai-1.3.0.dist-info/licenses/LICENSE
richmonokai/__init__.py
richmonokai/monokai.py
rich_monokai-1.3.0.dist-info/METADATA
rich_monokai-1.3.0.dist-info/WHEEL
rich_monokai-1.3.0.dist-info/top_level.txt
rich_monokai-1.3.0.dist-info/RECORD
