Metadata-Version: 2.4
Name: rich_monokai
Version: 1.3.0
Summary: A Monokai theme for the Textualize/rich Python package.
Home-page: https://github.com/chief8192/rich-monokai
Author: Matt Doyle
License: MIT
Keywords: rich,monokai
Classifier: Development Status :: 5 - Production/Stable
Classifier: License :: OSI Approved :: MIT License
Classifier: Programming Language :: Python :: 3
Requires-Python: >=3.0
License-File: LICENSE
Dynamic: home-page
Dynamic: license-file
